cartesian_explorer/Explorer.py
cartesian_explorer/ExplorerBasic.py
cartesian_explorer/__init__.py
cartesian_explorer/caches.py
cartesian_explorer/lazy_imports.py
cartesian_explorer/parallels.py
cartesian_explorer/lib/argument_inspect.py
cartesian_explorer/lib/dep_graph.py
cartesian_explorer/lib/dict_product.py
cartesian_explorer/lib/lru_cache.py
cartesian_explorer/lib/lru_cache_diskcache.py
cartesian_explorer/lib/lru_cache_mproc.py
cartesian_explorer/scratchpad/multiproc_share.py
cartesian_explorer-0.1.13.dist-info/AUTHORS.rst
cartesian_explorer-0.1.13.dist-info/LICENSE
cartesian_explorer-0.1.13.dist-info/METADATA
cartesian_explorer-0.1.13.dist-info/WHEEL
cartesian_explorer-0.1.13.dist-info/top_level.txt
cartesian_explorer-0.1.13.dist-info/RECORD
