Metadata-Version: 2.1
Name: cartesian-explorer
Version: 0.1.13
Summary: Utility to efficiently explore functions on their domains
Home-page: https://github.com/danlkv/cartesian-explorer
Author: Danylo Lykov
Author-email: lkvdan@gmail.com
License: MIT license
Keywords: cartesian_explorer
Platform: UNKNOWN
Classifier: Development Status :: 2 - Pre-Alpha
Classifier: Intended Audience :: Developers
Classifier: License :: OSI Approved :: MIT License
Classifier: Natural Language :: English
Classifier: Programming Language :: Python :: 3
Classifier: Programming Language :: Python :: 3.6
Classifier: Programming Language :: Python :: 3.7
Classifier: Programming Language :: Python :: 3.8
Requires-Python: >=3.5
Requires-Dist: Click (>=7.0)
Requires-Dist: tqdm
Requires-Dist: numpy
Requires-Dist: matplotlib
Requires-Dist: networkx
Requires-Dist: joblib
